identicons/__init__.py
identiconspy-1.0.0.dist-info/LICENSE
identiconspy-1.0.0.dist-info/METADATA
identiconspy-1.0.0.dist-info/WHEEL
identiconspy-1.0.0.dist-info/top_level.txt
identiconspy-1.0.0.dist-info/RECORD
