Metadata-Version: 2.1
Name: identiconspy
Version: 1.0.0
Summary: Identicons generator for python
Author: TheNoobiCat
Project-URL: Homepage, https://github.com/TheNoobiCat/identicons.py
Project-URL: Issues, https://github.com/TheNoobiCat/identicons.py/issues
Classifier: Programming Language :: Python :: 3
Classifier: License :: OSI Approved :: MIT License
Classifier: Operating System :: OS Independent
Requires-Python: >=3.8
License-File: LICENSE
